{
    "boxShadow": "none",
    "iconSVG": "/static/media/icon.f4dd498ee72f01127e5bfe3a1a8ad671.svg",
    "topRow": 7,
    "labelWidth": 5,
    "type": "INPUT_WIDGET_V2",
    "animateLoading": true,
    "resetOnSubmit": true,
    "leftColumn": 34,
    "dynamicBindingPathList": [
        {"key": "accentColor"},
        {"key": "borderRadius"}
    ],
    "labelStyle": "",
    "inputType": "TEXT",
    "isDisabled": false,
    "isRequired": false,
    "dynamicHeight": "FIXED",
    "accentColor": "{{appsmith.theme.colors.primaryColor}}",
    "showStepArrows": false,
    "isVisible": true,
    "version": 2,
    "tags": [
        "Suggested",
        "Inputs"
    ],
    "isLoading": false,
    "borderRadius": "{{appsmith.theme.borderRadius.appBorderRadius}}",
    "needsErrorInfo": false,
    "mobileBottomRow": 13,
    "widgetName": "Input1",
    "displayName": "Input",
    "searchTags": [
        "form",
        "text input",
        "number",
        "textarea"
    ],
    "bottomRow": 11,
    "parentRowSpace": 10,
    "autoFocus": false,
    "hideCard": false,
    "mobileRightColumn": 58,
    "parentColumnSpace": 10.233642578125,
    "dynamicTriggerPathList": [],
    "labelPosition": "Top",
    "key": "vh9j9av1m5",
    "labelTextSize": "0.875rem",
    "isDeprecated": false,
    "rightColumn": 50,
    "thumbnailSVG": "https://appcdn.appsmith.com/static/media/thumbnail.a4eac1a16753ea7fc54cac7731f9ea6a.svg",
    "widgetId": "cpuv66m9pt",
    "minWidth": 450,
    "label": "",
    "parentId": "80r7rohfxc",
    "labelAlignment": "left",
    "renderMode": "CANVAS",
    "mobileTopRow": 6,
    "responsiveBehavior": "fill",
    "mobileLeftColumn": 38,
    "maxDynamicHeight": 9000,
    "iconAlign": "left",
    "defaultText": "",
    "minDynamicHeight": 4
}